adorner/__init__.py
adorner/tools.py
adorner-1.0.1.dist-info/LICENSE
adorner-1.0.1.dist-info/METADATA
adorner-1.0.1.dist-info/WHEEL
adorner-1.0.1.dist-info/RECORD
