Metadata-Version: 2.1
Name: adorner
Version: 1.0.1
Summary: This is a modern lightweight Python decorator utility module.
Home-page: https://github.com/gupingan/adorner
License: MIT
Author: gupingan
Author-email: g332920287@foxmail.com
Requires-Python: >=3.7
Classifier: License :: OSI Approved :: MIT License
Classifier: Programming Language :: Python :: 3
Classifier: Programming Language :: Python :: 3.7
Classifier: Programming Language :: Python :: 3.8
Classifier: Programming Language :: Python :: 3.9
Classifier: Programming Language :: Python :: 3.10
Classifier: Programming Language :: Python :: 3.11
Classifier: Programming Language :: Python :: 3.12
Project-URL: Documentation, https://www.cnblogs.com/gupingan/p/18299851
Project-URL: Repository, https://github.com/gupingan/adorner
